test_cover/__init__.py
test_cover/html_test_result.py
test_cover/html_test_runner.py
test_cover/template/report_template.html
test_cover-0.1.0.dist-info/LICENSE
test_cover-0.1.0.dist-info/METADATA
test_cover-0.1.0.dist-info/WHEEL
test_cover-0.1.0.dist-info/top_level.txt
test_cover-0.1.0.dist-info/RECORD
