Metadata-Version: 2.2
Name: test_cover
Version: 0.1.0
Summary: A Test Runner in python, for Human Readable HTML Reports
Home-page: https://github.com/usalko/test_cover
Author: usalko
Author-email: ivict@rambler.ru
License: APACHE 2.0
Keywords: test_cover TestRunner Html Reports
Classifier: Development Status :: 4 - Beta
Classifier: Intended Audience :: Developers
Classifier: License :: OSI Approved :: Apache Software License
Classifier: Natural Language :: English
Classifier: Programming Language :: Python :: 3.5
License-File: LICENSE
Requires-Dist: Jinja2>=2.10.1
Dynamic: author
Dynamic: author-email
Dynamic: classifier
Dynamic: description
Dynamic: home-page
Dynamic: keywords
Dynamic: license
Dynamic: requires-dist
Dynamic: summary
